mvg_labs/__init__.py
mvg_labs-0.0.3.dist-info/METADATA
mvg_labs-0.0.3.dist-info/WHEEL
mvg_labs-0.0.3.dist-info/top_level.txt
mvg_labs-0.0.3.dist-info/RECORD
