Metadata-Version: 2.1
Name: mvg-labs
Version: 0.0.3
Summary: "A package for multi-view geometry"
License: MIT
Requires-Dist: numpy
